{
  "iteration": 4,
  "timestamp": 1771174099.2964468,
  "n_candidates": 8,
  "candidates": [
    {
      "formula": "Hf3Os",
      "method": "mix",
      "parent": "Li3 Pt1 \u00d7 Hf4 Os8",
      "mutations": "{'Li': np.str_('Hf'), 'Pt': np.str_('Os')}",
      "topo_probability": 1.0,
      "stability_score": 0.5,
      "heuristic_topo_score": 1.0,
      "novelty_score": 1.0,
      "acquisition_value": 0.875,
      "energy_per_atom": null,
      "converged": false,
      "iteration": 4
    },
    {
      "formula": "Hf3Os",
      "method": "mix",
      "parent": "Cu1 Pt3 \u00d7 Hf1 Os3",
      "mutations": "{'Cu': np.str_('Os'), 'Pt': np.str_('Hf')}",
      "topo_probability": 1.0,
      "stability_score": 0.5,
      "heuristic_topo_score": 1.0,
      "novelty_score": 1.0,
      "acquisition_value": 0.875,
      "energy_per_atom": null,
      "converged": false,
      "iteration": 4
    },
    {
      "formula": "Y7Os",
      "method": "mix",
      "parent": "Cu1 Pt7 \u00d7 Y4 Os8",
      "mutations": "{'Cu': np.str_('Os'), 'Pt': np.str_('Y')}",
      "topo_probability": 0.7746987951807229,
      "stability_score": 0.5,
      "heuristic_topo_score": 0.7746987951807229,
      "novelty_score": 1.0,
      "acquisition_value": 0.7510843373493976,
      "energy_per_atom": null,
      "converged": false,
      "iteration": 4
    },
    {
      "formula": "Na7(CdSn)2",
      "method": "mix",
      "parent": "Zn4 Fe14 O4 \u00d7 Na4 Cd2 Sn2",
      "mutations": "{'Fe': np.str_('Na'), 'O': np.str_('Cd'), 'Zn': np.str_('Sn')}",
      "topo_probability": 0.5807228915662651,
      "stability_score": 0.5,
      "heuristic_topo_score": 0.5807228915662651,
      "novelty_score": 1.0,
      "acquisition_value": 0.6443975903614458,
      "energy_per_atom": null,
      "converged": false,
      "iteration": 4
    },
    {
      "formula": "Pu3Ni",
      "method": "mix",
      "parent": "Y1 Os3 \u00d7 Pu1 Ni3",
      "mutations": "{'Os': np.str_('Pu'), 'Y': np.str_('Ni')}",
      "topo_probability": 0.5397590361445783,
      "stability_score": 0.5,
      "heuristic_topo_score": 0.5397590361445783,
      "novelty_score": 1.0,
      "acquisition_value": 0.6218674698795181,
      "energy_per_atom": null,
      "converged": false,
      "iteration": 4
    },
    {
      "formula": "PtRh2",
      "method": "mix",
      "parent": "Ti2 Re4 \u00d7 Pt2 Rh4",
      "mutations": "{'Re': np.str_('Rh'), 'Ti': np.str_('Pt')}",
      "topo_probability": 0.6819277108433734,
      "stability_score": 0.5,
      "heuristic_topo_score": 0.6819277108433734,
      "novelty_score": 0.2,
      "acquisition_value": 0.5400602409638554,
      "energy_per_atom": null,
      "converged": false,
      "iteration": 4
    },
    {
      "formula": "Li16Mn3Sn4O5",
      "method": "mix",
      "parent": "Li4 Mn3 Sn5 O16 \u00d7 Li8 Mn1 Sn2 O3",
      "mutations": "{'Li': np.str_('Sn'), 'Mn': np.str_('Mn'), 'O': np.str_('Li'), 'Sn': np.str_('O')}",
      "topo_probability": 0.38072289156626504,
      "stability_score": 0.5,
      "heuristic_topo_score": 0.38072289156626504,
      "novelty_score": 1.0,
      "acquisition_value": 0.5343975903614457,
      "energy_per_atom": null,
      "converged": false,
      "iteration": 4
    },
    {
      "formula": "Zn2FeO",
      "method": "mix",
      "parent": "Y2 Fe2 O4 \u00d7 Zn2 Fe4 O8",
      "mutations": "{'Fe': np.str_('O'), 'O': np.str_('Zn'), 'Y': np.str_('Fe')}",
      "topo_probability": 0.3,
      "stability_score": 0.5,
      "heuristic_topo_score": 0.3,
      "novelty_score": 1.0,
      "acquisition_value": 0.49,
      "energy_per_atom": null,
      "converged": false,
      "iteration": 4
    }
  ]
}